colorful_print/__init__.py
colorful_print/constants.py
colorful_print/printer.py
colorful_print/styler.py
colorful_print-1.0.0.dist-info/LICENSE
colorful_print-1.0.0.dist-info/METADATA
colorful_print-1.0.0.dist-info/WHEEL
colorful_print-1.0.0.dist-info/RECORD
