Metadata-Version: 2.1
Name: colorful-print
Version: 1.0.0
Summary: Can it be used to print in color.
Home-page: https://github.com/sanggi-wjg/color_print
License: MIT
Keywords: color,print,terminal,colorful,ansi
Author: SangGi
Author-email: girr311@naver.com
Requires-Python: >=3.8,<4.0
Classifier: License :: OSI Approved :: MIT License
Classifier: Operating System :: OS Independent
Classifier: Programming Language :: Python :: 3
Classifier: Programming Language :: Python :: 3.8
Classifier: Programming Language :: Python :: 3.9
Classifier: Programming Language :: Python :: 3.10
Classifier: Programming Language :: Python :: 3.11
Classifier: Programming Language :: Python :: 3.12
Classifier: Programming Language :: Python :: 3.13
Project-URL: Bug Tracker, https://github.com/sanggi-wjg/color_print/issues
Project-URL: Repository, https://github.com/sanggi-wjg/color_print
